jira_mcp_server/__init__.py
jira_mcp_server/server.py
mcp_jira_server-1.0.2.dist-info/licenses/LICENSE
mcp_jira_server-1.0.2.dist-info/METADATA
mcp_jira_server-1.0.2.dist-info/WHEEL
mcp_jira_server-1.0.2.dist-info/entry_points.txt
mcp_jira_server-1.0.2.dist-info/top_level.txt
mcp_jira_server-1.0.2.dist-info/RECORD
