Metadata-Version: 2.4
Name: mcp-jira-server
Version: 1.0.2
Summary: MCP server for Jira integration
Author-email: Prashant Bhapkar <your-email@example.com>
License: MIT
Project-URL: Homepage, https://pypi.org/project/mcp-jira-server/
Requires-Python: >=3.10
License-File: LICENSE
Requires-Dist: mcp[cli]
Requires-Dist: jira==3.8.0
Dynamic: license-file
